<TileDef-array>
  <TileDef>
    <colour>-16913</colour>
    <unknown>1</unknown>
    <objectType>0</objectType>
  </TileDef>
  <TileDef>
    <colour>1</colour>
    <unknown>3</unknown>
    <objectType>1</objectType>
  </TileDef>
  <TileDef>
    <colour>3</colour>
    <unknown>2</unknown>
    <objectType>0</objectType>
  </TileDef>
  <TileDef>
    <colour>3</colour>
    <unknown>4</unknown>
    <objectType>0</objectType>
  </TileDef>
  <TileDef>
    <colour>-16913</colour>
    <unknown>2</unknown>
    <objectType>0</objectType>
  </TileDef>
  <TileDef>
    <colour>-27685</colour>
    <unknown>2</unknown>
    <objectType>0</objectType>
  </TileDef>
  <TileDef>
    <colour>25</colour>
    <unknown>3</unknown>
    <objectType>1</objectType>
  </TileDef>
  <TileDef>
    <colour>12345678</colour>
    <unknown>5</unknown>
    <objectType>1</objectType>
  </TileDef>
  <TileDef>
    <colour>-26426</colour>
    <unknown>1</unknown>
    <objectType>1</objectType>
  </TileDef>
  <TileDef>
    <colour>-1</colour>
    <unknown>5</unknown>
    <objectType>1</objectType>
  </TileDef>
  <TileDef>
    <colour>31</colour>
    <unknown>3</unknown>
    <objectType>1</objectType>
  </TileDef>
  <TileDef>
    <colour>3</colour>
    <unknown>4</unknown>
    <objectType>0</objectType>
  </TileDef>
  <TileDef>
    <colour>-4534</colour>
    <unknown>2</unknown>
    <objectType>0</objectType>
  </TileDef>
  <TileDef>
    <colour>32</colour>
    <unknown>2</unknown>
    <objectType>0</objectType>
  </TileDef>
  <TileDef>
    <colour>-9225</colour>
    <unknown>2</unknown>
    <objectType>0</objectType>
  </TileDef>
  <TileDef>
    <colour>-3172</colour>
    <unknown>2</unknown>
    <objectType>0</objectType>
  </TileDef>
  <TileDef>
    <colour>15</colour>
    <unknown>2</unknown>
    <objectType>0</objectType>
  </TileDef>
  <TileDef>
    <colour>-2</colour>
    <unknown>2</unknown>
    <objectType>0</objectType>
  </TileDef>
  <TileDef>
    <colour>-1</colour>
    <unknown>3</unknown>
    <objectType>1</objectType>
  </TileDef>
  <TileDef>
    <colour>-2</colour>
    <unknown>4</unknown>
    <objectType>0</objectType>
  </TileDef>
  <TileDef>
    <colour>-2</colour>
    <unknown>4</unknown>
    <objectType>1</objectType>
  </TileDef>
  <TileDef>
    <colour>-2</colour>
    <unknown>0</unknown>
    <objectType>0</objectType>
  </TileDef>
  <TileDef>
    <colour>-17793</colour>
    <unknown>2</unknown>
    <objectType>0</objectType>
  </TileDef>
  <TileDef>
    <colour>-14594</colour>
    <unknown>1</unknown>
    <objectType>1</objectType>
  </TileDef>
  <TileDef>
    <colour>1</colour>
    <unknown>3</unknown>
    <objectType>0</objectType>
  </TileDef>
  <!-- Voidscape: Void Floor — primary courtyard tile (id 25). RGB555 (10, 10, 10) = -10571,
       renders RGB888 (80, 80, 80) — neutral medium-dark grey. Purple accents come from
       TileDef 26/27 (sigil dots + ritual circle). -->
  <TileDef>
    <colour>-10571</colour>
    <unknown>3</unknown>
    <objectType>0</objectType>
  </TileDef>
  <!-- Voidscape: Void Floor Accent (id 26). RGB555 (25, 6, 20) = -20698,
       renders RGB888 (200, 48, 160) — brighter magenta-purple. Used for the central
       ritual circle inside the sanctum AND scattered rune dots across the courtyard. -->
  <TileDef>
    <colour>-20698</colour>
    <unknown>3</unknown>
    <objectType>0</objectType>
  </TileDef>
  <!-- Voidscape: Void Floor Mid (id 27). RGB555 (15, 8, 18) = -16915,
       renders RGB888 (144, 64, 120) — mid-purple, used for accent rings around
       the central ritual circle to create depth. -->
  <TileDef>
    <colour>-16915</colour>
    <unknown>3</unknown>
    <objectType>0</objectType>
  </TileDef>
</TileDef-array>